{
    "id": "2022-09_creator_monetization_raven_users",
    "label": "Creator Monetization Onboarding v2 Users",
    "hash": 2539540256,
    "kind": "user",
    "treatments": [
        {
            "id": 1,
            "aa_mode": 0,
            "label": "Enables users to create Guild Role Subscriptions quickly"
        }
    ],
    "populations": [
        {
            "filter": [
                {
                    "type": 1175413786,
                    "data": [
                        "PL",
                        "SE",
                        "US"
                    ]
                }
            ],
            "rollout": [
                {
                    "treatment": 1,
                    "percentage": 100,
                    "ranges": [
                        {
                            "start": 0,
                            "end": 10000
                        }
                    ]
                }
            ]
        }
    ]
}