{
    "id": "2024-03_media_play_metrics",
    "label": "Media play metrics User Experiment",
    "hash": 465715532,
    "kind": "user",
    "aa_mode": 0,
    "hashkey": null,
    "treatments": [
        {
            "id": 0,
            "aa_mode": 0,
            "label": "Control"
        },
        {
            "id": 1,
            "aa_mode": 0,
            "label": "Send metrics"
        }
    ],
    "populations": [
        {
            "filter": null,
            "rollout": [
                {
                    "treatment": 1,
                    "percentage": 10,
                    "ranges": [
                        {
                            "start": 0,
                            "end": 1000
                        }
                    ]
                }
            ]
        }
    ]
}