{
    "id": "2024-09_message_forwarding_gtm",
    "label": "Message forwarding GTM",
    "hash": 1298178098,
    "kind": "user",
    "treatments": [
        {
            "id": 1,
            "aa_mode": 0,
            "label": "GTM"
        }
    ],
    "populations": [
        {
            "filter": [
                {
                    "type": 1175413786,
                    "data": [
                        "DE",
                        "SE",
                        "US"
                    ]
                }
            ],
            "rollout": [
                {
                    "treatment": 1,
                    "percentage": 95,
                    "ranges": [
                        {
                            "start": 0,
                            "end": 9000
                        },
                        {
                            "start": 9500,
                            "end": 10000
                        }
                    ]
                }
            ]
        }
    ]
}